{
    "monsterName": "Mastiff",
    "monsterType": "Medium beast, unaligned",
    "monsterArmor": "Armor Class 12",
    "monsterHP": "Hit Points 5 (1d8+1)",
    "monsterSpeed": "Speed 40 ft.",
    "monsterSTR": "13 (+1)",
    "monsterDEX": "14 (+2)",
    "monsterCON": "12 (+1)",
    "monsterINT": "3 (-4)",
    "monsterWIS": "12 (+1)",
    "monsterCHA": "7 (-2)",
    "monsterSavings": "",
    "monsterSkills": "Skills Perception +3",
    "monsterVulnerabilities": "",
    "monsterResistances": "",
    "monsterImmunities": "",
    "monsterCImmunities": "",
    "monsterSenses": "",
    "monsterLanguages": "",
    "monsterChallenge": "Challenge  1/8 (25 XP)",
    "monsterSpecials": [
        "Keen Hearing and Smell. The mastiff has advantage on Wisdom (Perception) checks that rely on hearing or smell."
    ],
    "monsterActions": [
        "_____________________ Actions _____________________",
        "Bite. Melee Weapon Attack: +3 to hit, reach 5 ft., one target. Hit: 4 (1d6 + 1) piercing damage. If the target is a creature, it must succeed on a DC 11 Strength saving throw or be knocked prone."
    ]
}