{
    "spellName": "Telekinesis",
    "spellSchool": "transmutation",
    "spellClasses": [
        "Sorcerer",
        "Wizard"
    ],
    "spellLevel": 5,
    "castingTime": "1 action",
    "spellDuration": "Concentration, up to 10 minutes",
    "spellRange": "60 feet",
    "spellEffect": "You gain the ability to move or manipulate creatures or objects by thought. When you cast the spell, and as your action each round for the duration, you can exert your will on one creature or object that you can see within range, causing the appropriate effect below. You can affect the same target round after round, or choose a new one at any time. If you switch targets, the prior target is no longer affected by the spell.",
    "verbalBool": "True",
    "somaticBool": "True",
    "materialBool": "False",
    "materials": "N/A",
    "spellSave": "--"
}